{
	"parameters": {
		"case_path": "C:\\ATTEST\\tools\\WP3\\T31V2\\pyensys/tests/matpower/case3.m",
		"attest_inputs_path": "C:\\ATTEST\\tools\\WP3\\T31V2\\tmp/case3_inputs.json",
		"output_path": "C:\\ATTEST\\tools\\WP3\\T31V2\\tmp/case3_outputs.json",
		"line_capacities": [
			0.045,
			0.075,
			0.1125,
			0.15,
			0.225,
			0.3,
			0.5,
			0.75,
			1.0,
			2.0,
			5.0,
			10.0,
			20.0,
			30.0,
			40.0,
			50.0,
			60.0,
			80.0,
			100.0,
			250.0,
			500.0
		],
		"TRS_capacities": [
			1.0,
			2.0,
			5.0,
			10.0,
			20.0,
			30.0,
			40.0,
			50.0,
			60.0,
			80.0,
			100.0,
			250.0,
			500.0
		],
		"line_costs": [],
		"TRS_costs": [],
		"cont_list": [],
		"line_length": [],
		"growth": {
			"Active": {
				"2020": 0,
				"2030": 1.89,
				"2040": 3.0
			},
			"Slow": {
				"2020": 0,
				"2030": 1.1,
				"2040": 2.0
			}
		},
		"DSR": {
			"Active": {
				"2020": 0,
				"2030": 0.05,
				"2040": 0.05
			},
			"Slow": {
				"2020": 0,
				"2030": 0.02,
				"2040": 0.02
			}
		},
		"oversize": 0,
		"Max_clusters": 3,
		"scenarios": [],
		"cluster": null,
		"use_load_data_update": 0,
		"add_load_data_case_name": "UK_Dx_01_",
		"EV_data_file_path": "C:\\ATTEST\\tools\\WP3\\T31V2\\tmp/EV-PV-Storage_Data_for_Simulations.xlsx"
	}
}